Workbook

Sheet Guia
A1: Libro de pruebas de fórmulas Excel
A2: Hojas | B2: Datos, Calculos, Texto_Fecha, Busquedas, Validaciones, Matrices
A3: Contenido | B3: Más de 300 fórmulas; expresiones Excel en inglés.
A4: Nota | B4: Algunas bibliotecas leen fórmulas pero no las calculan; Excel o LibreOffice puede recalcular al abrir.

Sheet Datos
A1: ID | B1: Nombre | C1: Apellido | D1: Departamento | E1: Ciudad | F1: Unidades | G1: Precio | H1: Descuento | I1: Fecha | J1: Estado | K1: Correo
A2: 1001 | B2: Ana | C2: López | D2: Ventas | E2: Guatemala | F2: 8 | G2: 21.25 | H2: 0.05 | I2: 46026 | J2: Cerrado | K2: ana.lópez@ejemplo.com
A3: 1002 | B3: Luis | C3: Méndez | D3: Soporte | E3: Antigua | F3: 15 | G3: 30 | H3: 0.1 | I3: 46029 | J3: Pendiente | K3: luis.méndez@ejemplo.com
A4: 1003 | B4: Marta | C4: García | D4: Finanzas | E4: Quetzaltenango | F4: 22 | G4: 38.75 | H4: 0.15 | I4: 46032 | J4: Abierto | K4: marta.garcía@ejemplo.com
A5: 1004 | B5: José | C5: Ramírez | D5: Ventas | E5: Guatemala | F5: 6 | G5: 47.5 | H5: 0 | I5: 46035 | J5: Cerrado | K5: josé.ramírez@ejemplo.com
A6: 1005 | B6: Sofía | C6: Hernández | D6: Operaciones | E6: Escuintla | F6: 13 | G6: 56.25 | H6: 0.05 | I6: 46038 | J6: Pendiente | K6: sofía.hernández@ejemplo.com
A7: 1006 | B7: Carlos | C7: Morales | D7: Soporte | E7: Cobán | F7: 20 | G7: 65 | H7: 0.1 | I7: 46041 | J7: Abierto | K7: carlos.morales@ejemplo.com
A8: 1007 | B8: Elena | C8: Castillo | D8: Ventas | E8: Antigua | F8: 4 | G8: 73.75 | H8: 0.15 | I8: 46044 | J8: Cerrado | K8: elena.castillo@ejemplo.com
A9: 1008 | B9: Diego | C9: Pérez | D9: Finanzas | E9: Guatemala | F9: 11 | G9: 82.5 | H9: 0 | I9: 46047 | J9: Pendiente | K9: diego.pérez@ejemplo.com
A10: 1009 | B10: Lucía | C10: Gómez | D10: Operaciones | E10: Petén | F10: 18 | G10: 12.5 | H10: 0.05 | I10: 46050 | J10: Abierto | K10: lucía.gómez@ejemplo.com
A11: 1010 | B11: Pablo | C11: Ruiz | D11: Soporte | E11: Quetzaltenango | F11: 2 | G11: 21.25 | H11: 0.1 | I11: 46053 | J11: Cerrado | K11: pablo.ruiz@ejemplo.com
A12: 1011 | B12: Ana | C12: López | D12: Ventas | E12: Guatemala | F12: 9 | G12: 30 | H12: 0.15 | I12: 46056 | J12: Pendiente | K12: ana.lópez@ejemplo.com
A13: 1012 | B13: Luis | C13: Méndez | D13: Soporte | E13: Antigua | F13: 16 | G13: 38.75 | H13: 0 | I13: 46059 | J13: Abierto | K13: luis.méndez@ejemplo.com
... A51: 1050 | B51: Pablo | C51: Ruiz | D51: Soporte | E51: Quetzaltenango | F51: 6 | G51: 56.25 | H51: 0.1 | I51: 46173 | J51: Pendiente | K51: pablo.ruiz@ejemplo.com

Sheet Calculos
A1: ID | B1: Importe bruto | C1: Importe neto | D1: Impuesto | E1: Total | F1: IF | G1: IFS | H1: AND | I1: OR | J1: IFERROR | K1: SUMIF dep. | L1: COUNTIF estado | M1: AVERAGEIF dep. | N1: MAX | O1: MIN | P1: ROUND | Q1: MOD | R1: ABS | S1: SQRT | T1: POWER | U1: RANK
A2: =Datos!A2 | B2: =Datos!F2*Datos!G2 | C2: =B2*(1-Datos!H2) | D2: =C2*0.12 | E2: =C2+D2 | F2: =IF(E2>=200,"Alto","Normal") | G2: =IFS(E2>=400,"Premium",E2>=200,"Medio",TRUE,"Bajo") | H2: =AND(Datos!F2>0,Datos!G2>0) | I2: =OR(Datos!J2="Abierto",Datos!J2="Pendiente") | J2: =IFERROR(B2/(Datos!F2-Datos!F2),"Sin división") | K2: =SUMIF(Datos!D$2:D$51,Datos!D2,Calculos!C$2:C$51) | L2: =COUNTIF(Datos!J$2:J$51,Datos!J2) | M2: =AVERAGEIF(Datos!D$2:D$51,Datos!D2,Calculos!E$2:E$51) | N2: =MAX(B$2:B$51) | O2: =MIN(B$2:B$51) | P2: =ROUND(E2,2) | Q2: =MOD(Datos!F2,5) | R2: =ABS(Datos!H2-0.1) | S2: =SQRT(Datos!F2) | T2: =POWER(Datos!G2,2) | U2: =RANK(E2,E$2:E$51,0)
A3: =Datos!A3 | B3: =Datos!F3*Datos!G3 | C3: =B3*(1-Datos!H3) | D3: =C3*0.12 | E3: =C3+D3 | F3: =IF(E3>=200,"Alto","Normal") | G3: =IFS(E3>=400,"Premium",E3>=200,"Medio",TRUE,"Bajo") | H3: =AND(Datos!F3>0,Datos!G3>0) | I3: =OR(Datos!J3="Abierto",Datos!J3="Pendiente") | J3: =IFERROR(B3/(Datos!F3-Datos!F3),"Sin división") | K3: =SUMIF(Datos!D$2:D$51,Datos!D3,Calculos!C$2:C$51) | L3: =COUNTIF(Datos!J$2:J$51,Datos!J3) | M3: =AVERAGEIF(Datos!D$2:D$51,Datos!D3,Calculos!E$2:E$51) | N3: =MAX(B$2:B$51) | O3: =MIN(B$2:B$51) | P3: =ROUND(E3,2) | Q3: =MOD(Datos!F3,5) | R3: =ABS(Datos!H3-0.1) | S3: =SQRT(Datos!F3) | T3: =POWER(Datos!G3,2) | U3: =RANK(E3,E$2:E$51,0)
A4: =Datos!A4 | B4: =Datos!F4*Datos!G4 | C4: =B4*(1-Datos!H4) | D4: =C4*0.12 | E4: =C4+D4 | F4: =IF(E4>=200,"Alto","Normal") | G4: =IFS(E4>=400,"Premium",E4>=200,"Medio",TRUE,"Bajo") | H4: =AND(Datos!F4>0,Datos!G4>0) | I4: =OR(Datos!J4="Abierto",Datos!J4="Pendiente") | J4: =IFERROR(B4/(Datos!F4-Datos!F4),"Sin división") | K4: =SUMIF(Datos!D$2:D$51,Datos!D4,Calculos!C$2:C$51) | L4: =COUNTIF(Datos!J$2:J$51,Datos!J4) | M4: =AVERAGEIF(Datos!D$2:D$51,Datos!D4,Calculos!E$2:E$51) | N4: =MAX(B$2:B$51) | O4: =MIN(B$2:B$51) | P4: =ROUND(E4,2) | Q4: =MOD(Datos!F4,5) | R4: =ABS(Datos!H4-0.1) | S4: =SQRT(Datos!F4) | T4: =POWER(Datos!G4,2) | U4: =RANK(E4,E$2:E$51,0)
A5: =Datos!A5 | B5: =Datos!F5*Datos!G5 | C5: =B5*(1-Datos!H5) | D5: =C5*0.12 | E5: =C5+D5 | F5: =IF(E5>=200,"Alto","Normal") | G5: =IFS(E5>=400,"Premium",E5>=200,"Medio",TRUE,"Bajo") | H5: =AND(Datos!F5>0,Datos!G5>0) | I5: =OR(Datos!J5="Abierto",Datos!J5="Pendiente") | J5: =IFERROR(B5/(Datos!F5-Datos!F5),"Sin división") | K5: =SUMIF(Datos!D$2:D$51,Datos!D5,Calculos!C$2:C$51) | L5: =COUNTIF(Datos!J$2:J$51,Datos!J5) | M5: =AVERAGEIF(Datos!D$2:D$51,Datos!D5,Calculos!E$2:E$51) | N5: =MAX(B$2:B$51) | O5: =MIN(B$2:B$51) | P5: =ROUND(E5,2) | Q5: =MOD(Datos!F5,5) | R5: =ABS(Datos!H5-0.1) | S5: =SQRT(Datos!F5) | T5: =POWER(Datos!G5,2) | U5: =RANK(E5,E$2:E$51,0)
A6: =Datos!A6 | B6: =Datos!F6*Datos!G6 | C6: =B6*(1-Datos!H6) | D6: =C6*0.12 | E6: =C6+D6 | F6: =IF(E6>=200,"Alto","Normal") | G6: =IFS(E6>=400,"Premium",E6>=200,"Medio",TRUE,"Bajo") | H6: =AND(Datos!F6>0,Datos!G6>0) | I6: =OR(Datos!J6="Abierto",Datos!J6="Pendiente") | J6: =IFERROR(B6/(Datos!F6-Datos!F6),"Sin división") | K6: =SUMIF(Datos!D$2:D$51,Datos!D6,Calculos!C$2:C$51) | L6: =COUNTIF(Datos!J$2:J$51,Datos!J6) | M6: =AVERAGEIF(Datos!D$2:D$51,Datos!D6,Calculos!E$2:E$51) | N6: =MAX(B$2:B$51) | O6: =MIN(B$2:B$51) | P6: =ROUND(E6,2) | Q6: =MOD(Datos!F6,5) | R6: =ABS(Datos!H6-0.1) | S6: =SQRT(Datos!F6) | T6: =POWER(Datos!G6,2) | U6: =RANK(E6,E$2:E$51,0)
A7: =Datos!A7 | B7: =Datos!F7*Datos!G7 | C7: =B7*(1-Datos!H7) | D7: =C7*0.12 | E7: =C7+D7 | F7: =IF(E7>=200,"Alto","Normal") | G7: =IFS(E7>=400,"Premium",E7>=200,"Medio",TRUE,"Bajo") | H7: =AND(Datos!F7>0,Datos!G7>0) | I7: =OR(Datos!J7="Abierto",Datos!J7="Pendiente") | J7: =IFERROR(B7/(Datos!F7-Datos!F7),"Sin división") | K7: =SUMIF(Datos!D$2:D$51,Datos!D7,Calculos!C$2:C$51) | L7: =COUNTIF(Datos!J$2:J$51,Datos!J7) | M7: =AVERAGEIF(Datos!D$2:D$51,Datos!D7,Calculos!E$2:E$51) | N7: =MAX(B$2:B$51) | O7: =MIN(B$2:B$51) | P7: =ROUND(E7,2) | Q7: =MOD(Datos!F7,5) | R7: =ABS(Datos!H7-0.1) | S7: =SQRT(Datos!F7) | T7: =POWER(Datos!G7,2) | U7: =RANK(E7,E$2:E$51,0)
A8: =Datos!A8 | B8: =Datos!F8*Datos!G8 | C8: =B8*(1-Datos!H8) | D8: =C8*0.12 | E8: =C8+D8 | F8: =IF(E8>=200,"Alto","Normal") | G8: =IFS(E8>=400,"Premium",E8>=200,"Medio",TRUE,"Bajo") | H8: =AND(Datos!F8>0,Datos!G8>0) | I8: =OR(Datos!J8="Abierto",Datos!J8="Pendiente") | J8: =IFERROR(B8/(Datos!F8-Datos!F8),"Sin división") | K8: =SUMIF(Datos!D$2:D$51,Datos!D8,Calculos!C$2:C$51) | L8: =COUNTIF(Datos!J$2:J$51,Datos!J8) | M8: =AVERAGEIF(Datos!D$2:D$51,Datos!D8,Calculos!E$2:E$51) | N8: =MAX(B$2:B$51) | O8: =MIN(B$2:B$51) | P8: =ROUND(E8,2) | Q8: =MOD(Datos!F8,5) | R8: =ABS(Datos!H8-0.1) | S8: =SQRT(Datos!F8) | T8: =POWER(Datos!G8,2) | U8: =RANK(E8,E$2:E$51,0)
A9: =Datos!A9 | B9: =Datos!F9*Datos!G9 | C9: =B9*(1-Datos!H9) | D9: =C9*0.12 | E9: =C9+D9 | F9: =IF(E9>=200,"Alto","Normal") | G9: =IFS(E9>=400,"Premium",E9>=200,"Medio",TRUE,"Bajo") | H9: =AND(Datos!F9>0,Datos!G9>0) | I9: =OR(Datos!J9="Abierto",Datos!J9="Pendiente") | J9: =IFERROR(B9/(Datos!F9-Datos!F9),"Sin división") | K9: =SUMIF(Datos!D$2:D$51,Datos!D9,Calculos!C$2:C$51) | L9: =COUNTIF(Datos!J$2:J$51,Datos!J9) | M9: =AVERAGEIF(Datos!D$2:D$51,Datos!D9,Calculos!E$2:E$51) | N9: =MAX(B$2:B$51) | O9: =MIN(B$2:B$51) | P9: =ROUND(E9,2) | Q9: =MOD(Datos!F9,5) | R9: =ABS(Datos!H9-0.1) | S9: =SQRT(Datos!F9) | T9: =POWER(Datos!G9,2) | U9: =RANK(E9,E$2:E$51,0)
A10: =Datos!A10 | B10: =Datos!F10*Datos!G10 | C10: =B10*(1-Datos!H10) | D10: =C10*0.12 | E10: =C10+D10 | F10: =IF(E10>=200,"Alto","Normal") | G10: =IFS(E10>=400,"Premium",E10>=200,"Medio",TRUE,"Bajo") | H10: =AND(Datos!F10>0,Datos!G10>0) | I10: =OR(Datos!J10="Abierto",Datos!J10="Pendiente") | J10: =IFERROR(B10/(Datos!F10-Datos!F10),"Sin división") | K10: =SUMIF(Datos!D$2:D$51,Datos!D10,Calculos!C$2:C$51) | L10: =COUNTIF(Datos!J$2:J$51,Datos!J10) | M10: =AVERAGEIF(Datos!D$2:D$51,Datos!D10,Calculos!E$2:E$51) | N10: =MAX(B$2:B$51) | O10: =MIN(B$2:B$51) | P10: =ROUND(E10,2) | Q10: =MOD(Datos!F10,5) | R10: =ABS(Datos!H10-0.1) | S10: =SQRT(Datos!F10) | T10: =POWER(Datos!G10,2) | U10: =RANK(E10,E$2:E$51,0)
A11: =Datos!A11 | B11: =Datos!F11*Datos!G11 | C11: =B11*(1-Datos!H11) | D11: =C11*0.12 | E11: =C11+D11 | F11: =IF(E11>=200,"Alto","Normal") | G11: =IFS(E11>=400,"Premium",E11>=200,"Medio",TRUE,"Bajo") | H11: =AND(Datos!F11>0,Datos!G11>0) | I11: =OR(Datos!J11="Abierto",Datos!J11="Pendiente") | J11: =IFERROR(B11/(Datos!F11-Datos!F11),"Sin división") | K11: =SUMIF(Datos!D$2:D$51,Datos!D11,Calculos!C$2:C$51) | L11: =COUNTIF(Datos!J$2:J$51,Datos!J11) | M11: =AVERAGEIF(Datos!D$2:D$51,Datos!D11,Calculos!E$2:E$51) | N11: =MAX(B$2:B$51) | O11: =MIN(B$2:B$51) | P11: =ROUND(E11,2) | Q11: =MOD(Datos!F11,5) | R11: =ABS(Datos!H11-0.1) | S11: =SQRT(Datos!F11) | T11: =POWER(Datos!G11,2) | U11: =RANK(E11,E$2:E$51,0)
A12: =Datos!A12 | B12: =Datos!F12*Datos!G12 | C12: =B12*(1-Datos!H12) | D12: =C12*0.12 | E12: =C12+D12 | F12: =IF(E12>=200,"Alto","Normal") | G12: =IFS(E12>=400,"Premium",E12>=200,"Medio",TRUE,"Bajo") | H12: =AND(Datos!F12>0,Datos!G12>0) | I12: =OR(Datos!J12="Abierto",Datos!J12="Pendiente") | J12: =IFERROR(B12/(Datos!F12-Datos!F12),"Sin división") | K12: =SUMIF(Datos!D$2:D$51,Datos!D12,Calculos!C$2:C$51) | L12: =COUNTIF(Datos!J$2:J$51,Datos!J12) | M12: =AVERAGEIF(Datos!D$2:D$51,Datos!D12,Calculos!E$2:E$51) | N12: =MAX(B$2:B$51) | O12: =MIN(B$2:B$51) | P12: =ROUND(E12,2) | Q12: =MOD(Datos!F12,5) | R12: =ABS(Datos!H12-0.1) | S12: =SQRT(Datos!F12) | T12: =POWER(Datos!G12,2) | U12: =RANK(E12,E$2:E$51,0)
A13: =Datos!A13 | B13: =Datos!F13*Datos!G13 | C13: =B13*(1-Datos!H13) | D13: =C13*0.12 | E13: =C13+D13 | F13: =IF(E13>=200,"Alto","Normal") | G13: =IFS(E13>=400,"Premium",E13>=200,"Medio",TRUE,"Bajo") | H13: =AND(Datos!F13>0,Datos!G13>0) | I13: =OR(Datos!J13="Abierto",Datos!J13="Pendiente") | J13: =IFERROR(B13/(Datos!F13-Datos!F13),"Sin división") | K13: =SUMIF(Datos!D$2:D$51,Datos!D13,Calculos!C$2:C$51) | L13: =COUNTIF(Datos!J$2:J$51,Datos!J13) | M13: =AVERAGEIF(Datos!D$2:D$51,Datos!D13,Calculos!E$2:E$51) | N13: =MAX(B$2:B$51) | O13: =MIN(B$2:B$51) | P13: =ROUND(E13,2) | Q13: =MOD(Datos!F13,5) | R13: =ABS(Datos!H13-0.1) | S13: =SQRT(Datos!F13) | T13: =POWER(Datos!G13,2) | U13: =RANK(E13,E$2:E$51,0)
... A51: =Datos!A51 | B51: =Datos!F51*Datos!G51 | C51: =B51*(1-Datos!H51) | D51: =C51*0.12 | E51: =C51+D51 | F51: =IF(E51>=200,"Alto","Normal") | G51: =IFS(E51>=400,"Premium",E51>=200,"Medio",TRUE,"Bajo") | H51: =AND(Datos!F51>0,Datos!G51>0) | I51: =OR(Datos!J51="Abierto",Datos!J51="Pendiente") | J51: =IFERROR(B51/(Datos!F51-Datos!F51),"Sin división") | K51: =SUMIF(Datos!D$2:D$51,Datos!D51,Calculos!C$2:C$51) | L51: =COUNTIF(Datos!J$2:J$51,Datos!J51) | M51: =AVERAGEIF(Datos!D$2:D$51,Datos!D51,Calculos!E$2:E$51) | N51: =MAX(B$2:B$51) | O51: =MIN(B$2:B$51) | P51: =ROUND(E51,2) | Q51: =MOD(Datos!F51,5) | R51: =ABS(Datos!H51-0.1) | S51: =SQRT(Datos!F51) | T51: =POWER(Datos!G51,2) | U51: =RANK(E51,E$2:E$51,0)

Sheet Texto_Fecha
A1: ID | B1: Nombre completo (&) | C1: CONCAT | D1: CONCATENATE | E1: UPPER | F1: LOWER | G1: PROPER | H1: LEFT | I1: RIGHT | J1: MID | K1: LEN | L1: FIND | M1: SUBSTITUTE | N1: TRIM | O1: TEXT | P1: DATE | Q1: YEAR | R1: MONTH | S1: DAY | T1: WEEKDAY | U1: EDATE | V1: EOMONTH | W1: Días transcurridos | X1: NETWORKDAYS
A2: =Datos!A2 | B2: =Datos!B2&" "&Datos!C2 | C2: =CONCAT(Datos!B2," ",Datos!C2) | D2: =CONCATENATE(Datos!B2,"-",Datos!C2) | E2: =UPPER(B2) | F2: =LOWER(B2) | G2: =PROPER(B2) | H2: =LEFT(B2,3) | I2: =RIGHT(B2,4) | J2: =MID(B2,2,5) | K2: =LEN(B2) | L2: =FIND(" ",B2) | M2: =SUBSTITUTE(B2," ","_") | N2: =TRIM(" "&B2&" ") | O2: =TEXT(Datos!I2,"yyyy-mm-dd") | P2: =DATE(YEAR(Datos!I2),MONTH(Datos!I2),DAY(Datos!I2)) | Q2: =YEAR(Datos!I2) | R2: =MONTH(Datos!I2) | S2: =DAY(Datos!I2) | T2: =WEEKDAY(Datos!I2,2) | U2: =EDATE(Datos!I2,2) | V2: =EOMONTH(Datos!I2,0) | W2: =TODAY()-Datos!I2 | X2: =NETWORKDAYS(Datos!I2,Datos!I2+10)
A3: =Datos!A3 | B3: =Datos!B3&" "&Datos!C3 | C3: =CONCAT(Datos!B3," ",Datos!C3) | D3: =CONCATENATE(Datos!B3,"-",Datos!C3) | E3: =UPPER(B3) | F3: =LOWER(B3) | G3: =PROPER(B3) | H3: =LEFT(B3,3) | I3: =RIGHT(B3,4) | J3: =MID(B3,2,5) | K3: =LEN(B3) | L3: =FIND(" ",B3) | M3: =SUBSTITUTE(B3," ","_") | N3: =TRIM(" "&B3&" ") | O3: =TEXT(Datos!I3,"yyyy-mm-dd") | P3: =DATE(YEAR(Datos!I3),MONTH(Datos!I3),DAY(Datos!I3)) | Q3: =YEAR(Datos!I3) | R3: =MONTH(Datos!I3) | S3: =DAY(Datos!I3) | T3: =WEEKDAY(Datos!I3,2) | U3: =EDATE(Datos!I3,2) | V3: =EOMONTH(Datos!I3,0) | W3: =TODAY()-Datos!I3 | X3: =NETWORKDAYS(Datos!I3,Datos!I3+10)
A4: =Datos!A4 | B4: =Datos!B4&" "&Datos!C4 | C4: =CONCAT(Datos!B4," ",Datos!C4) | D4: =CONCATENATE(Datos!B4,"-",Datos!C4) | E4: =UPPER(B4) | F4: =LOWER(B4) | G4: =PROPER(B4) | H4: =LEFT(B4,3) | I4: =RIGHT(B4,4) | J4: =MID(B4,2,5) | K4: =LEN(B4) | L4: =FIND(" ",B4) | M4: =SUBSTITUTE(B4," ","_") | N4: =TRIM(" "&B4&" ") | O4: =TEXT(Datos!I4,"yyyy-mm-dd") | P4: =DATE(YEAR(Datos!I4),MONTH(Datos!I4),DAY(Datos!I4)) | Q4: =YEAR(Datos!I4) | R4: =MONTH(Datos!I4) | S4: =DAY(Datos!I4) | T4: =WEEKDAY(Datos!I4,2) | U4: =EDATE(Datos!I4,2) | V4: =EOMONTH(Datos!I4,0) | W4: =TODAY()-Datos!I4 | X4: =NETWORKDAYS(Datos!I4,Datos!I4+10)
A5: =Datos!A5 | B5: =Datos!B5&" "&Datos!C5 | C5: =CONCAT(Datos!B5," ",Datos!C5) | D5: =CONCATENATE(Datos!B5,"-",Datos!C5) | E5: =UPPER(B5) | F5: =LOWER(B5) | G5: =PROPER(B5) | H5: =LEFT(B5,3) | I5: =RIGHT(B5,4) | J5: =MID(B5,2,5) | K5: =LEN(B5) | L5: =FIND(" ",B5) | M5: =SUBSTITUTE(B5," ","_") | N5: =TRIM(" "&B5&" ") | O5: =TEXT(Datos!I5,"yyyy-mm-dd") | P5: =DATE(YEAR(Datos!I5),MONTH(Datos!I5),DAY(Datos!I5)) | Q5: =YEAR(Datos!I5) | R5: =MONTH(Datos!I5) | S5: =DAY(Datos!I5) | T5: =WEEKDAY(Datos!I5,2) | U5: =EDATE(Datos!I5,2) | V5: =EOMONTH(Datos!I5,0) | W5: =TODAY()-Datos!I5 | X5: =NETWORKDAYS(Datos!I5,Datos!I5+10)
A6: =Datos!A6 | B6: =Datos!B6&" "&Datos!C6 | C6: =CONCAT(Datos!B6," ",Datos!C6) | D6: =CONCATENATE(Datos!B6,"-",Datos!C6) | E6: =UPPER(B6) | F6: =LOWER(B6) | G6: =PROPER(B6) | H6: =LEFT(B6,3) | I6: =RIGHT(B6,4) | J6: =MID(B6,2,5) | K6: =LEN(B6) | L6: =FIND(" ",B6) | M6: =SUBSTITUTE(B6," ","_") | N6: =TRIM(" "&B6&" ") | O6: =TEXT(Datos!I6,"yyyy-mm-dd") | P6: =DATE(YEAR(Datos!I6),MONTH(Datos!I6),DAY(Datos!I6)) | Q6: =YEAR(Datos!I6) | R6: =MONTH(Datos!I6) | S6: =DAY(Datos!I6) | T6: =WEEKDAY(Datos!I6,2) | U6: =EDATE(Datos!I6,2) | V6: =EOMONTH(Datos!I6,0) | W6: =TODAY()-Datos!I6 | X6: =NETWORKDAYS(Datos!I6,Datos!I6+10)
A7: =Datos!A7 | B7: =Datos!B7&" "&Datos!C7 | C7: =CONCAT(Datos!B7," ",Datos!C7) | D7: =CONCATENATE(Datos!B7,"-",Datos!C7) | E7: =UPPER(B7) | F7: =LOWER(B7) | G7: =PROPER(B7) | H7: =LEFT(B7,3) | I7: =RIGHT(B7,4) | J7: =MID(B7,2,5) | K7: =LEN(B7) | L7: =FIND(" ",B7) | M7: =SUBSTITUTE(B7," ","_") | N7: =TRIM(" "&B7&" ") | O7: =TEXT(Datos!I7,"yyyy-mm-dd") | P7: =DATE(YEAR(Datos!I7),MONTH(Datos!I7),DAY(Datos!I7)) | Q7: =YEAR(Datos!I7) | R7: =MONTH(Datos!I7) | S7: =DAY(Datos!I7) | T7: =WEEKDAY(Datos!I7,2) | U7: =EDATE(Datos!I7,2) | V7: =EOMONTH(Datos!I7,0) | W7: =TODAY()-Datos!I7 | X7: =NETWORKDAYS(Datos!I7,Datos!I7+10)
A8: =Datos!A8 | B8: =Datos!B8&" "&Datos!C8 | C8: =CONCAT(Datos!B8," ",Datos!C8) | D8: =CONCATENATE(Datos!B8,"-",Datos!C8) | E8: =UPPER(B8) | F8: =LOWER(B8) | G8: =PROPER(B8) | H8: =LEFT(B8,3) | I8: =RIGHT(B8,4) | J8: =MID(B8,2,5) | K8: =LEN(B8) | L8: =FIND(" ",B8) | M8: =SUBSTITUTE(B8," ","_") | N8: =TRIM(" "&B8&" ") | O8: =TEXT(Datos!I8,"yyyy-mm-dd") | P8: =DATE(YEAR(Datos!I8),MONTH(Datos!I8),DAY(Datos!I8)) | Q8: =YEAR(Datos!I8) | R8: =MONTH(Datos!I8) | S8: =DAY(Datos!I8) | T8: =WEEKDAY(Datos!I8,2) | U8: =EDATE(Datos!I8,2) | V8: =EOMONTH(Datos!I8,0) | W8: =TODAY()-Datos!I8 | X8: =NETWORKDAYS(Datos!I8,Datos!I8+10)
A9: =Datos!A9 | B9: =Datos!B9&" "&Datos!C9 | C9: =CONCAT(Datos!B9," ",Datos!C9) | D9: =CONCATENATE(Datos!B9,"-",Datos!C9) | E9: =UPPER(B9) | F9: =LOWER(B9) | G9: =PROPER(B9) | H9: =LEFT(B9,3) | I9: =RIGHT(B9,4) | J9: =MID(B9,2,5) | K9: =LEN(B9) | L9: =FIND(" ",B9) | M9: =SUBSTITUTE(B9," ","_") | N9: =TRIM(" "&B9&" ") | O9: =TEXT(Datos!I9,"yyyy-mm-dd") | P9: =DATE(YEAR(Datos!I9),MONTH(Datos!I9),DAY(Datos!I9)) | Q9: =YEAR(Datos!I9) | R9: =MONTH(Datos!I9) | S9: =DAY(Datos!I9) | T9: =WEEKDAY(Datos!I9,2) | U9: =EDATE(Datos!I9,2) | V9: =EOMONTH(Datos!I9,0) | W9: =TODAY()-Datos!I9 | X9: =NETWORKDAYS(Datos!I9,Datos!I9+10)
A10: =Datos!A10 | B10: =Datos!B10&" "&Datos!C10 | C10: =CONCAT(Datos!B10," ",Datos!C10) | D10: =CONCATENATE(Datos!B10,"-",Datos!C10) | E10: =UPPER(B10) | F10: =LOWER(B10) | G10: =PROPER(B10) | H10: =LEFT(B10,3) | I10: =RIGHT(B10,4) | J10: =MID(B10,2,5) | K10: =LEN(B10) | L10: =FIND(" ",B10) | M10: =SUBSTITUTE(B10," ","_") | N10: =TRIM(" "&B10&" ") | O10: =TEXT(Datos!I10,"yyyy-mm-dd") | P10: =DATE(YEAR(Datos!I10),MONTH(Datos!I10),DAY(Datos!I10)) | Q10: =YEAR(Datos!I10) | R10: =MONTH(Datos!I10) | S10: =DAY(Datos!I10) | T10: =WEEKDAY(Datos!I10,2) | U10: =EDATE(Datos!I10,2) | V10: =EOMONTH(Datos!I10,0) | W10: =TODAY()-Datos!I10 | X10: =NETWORKDAYS(Datos!I10,Datos!I10+10)
A11: =Datos!A11 | B11: =Datos!B11&" "&Datos!C11 | C11: =CONCAT(Datos!B11," ",Datos!C11) | D11: =CONCATENATE(Datos!B11,"-",Datos!C11) | E11: =UPPER(B11) | F11: =LOWER(B11) | G11: =PROPER(B11) | H11: =LEFT(B11,3) | I11: =RIGHT(B11,4) | J11: =MID(B11,2,5) | K11: =LEN(B11) | L11: =FIND(" ",B11) | M11: =SUBSTITUTE(B11," ","_") | N11: =TRIM(" "&B11&" ") | O11: =TEXT(Datos!I11,"yyyy-mm-dd") | P11: =DATE(YEAR(Datos!I11),MONTH(Datos!I11),DAY(Datos!I11)) | Q11: =YEAR(Datos!I11) | R11: =MONTH(Datos!I11) | S11: =DAY(Datos!I11) | T11: =WEEKDAY(Datos!I11,2) | U11: =EDATE(Datos!I11,2) | V11: =EOMONTH(Datos!I11,0) | W11: =TODAY()-Datos!I11 | X11: =NETWORKDAYS(Datos!I11,Datos!I11+10)
A12: =Datos!A12 | B12: =Datos!B12&" "&Datos!C12 | C12: =CONCAT(Datos!B12," ",Datos!C12) | D12: =CONCATENATE(Datos!B12,"-",Datos!C12) | E12: =UPPER(B12) | F12: =LOWER(B12) | G12: =PROPER(B12) | H12: =LEFT(B12,3) | I12: =RIGHT(B12,4) | J12: =MID(B12,2,5) | K12: =LEN(B12) | L12: =FIND(" ",B12) | M12: =SUBSTITUTE(B12," ","_") | N12: =TRIM(" "&B12&" ") | O12: =TEXT(Datos!I12,"yyyy-mm-dd") | P12: =DATE(YEAR(Datos!I12),MONTH(Datos!I12),DAY(Datos!I12)) | Q12: =YEAR(Datos!I12) | R12: =MONTH(Datos!I12) | S12: =DAY(Datos!I12) | T12: =WEEKDAY(Datos!I12,2) | U12: =EDATE(Datos!I12,2) | V12: =EOMONTH(Datos!I12,0) | W12: =TODAY()-Datos!I12 | X12: =NETWORKDAYS(Datos!I12,Datos!I12+10)
A13: =Datos!A13 | B13: =Datos!B13&" "&Datos!C13 | C13: =CONCAT(Datos!B13," ",Datos!C13) | D13: =CONCATENATE(Datos!B13,"-",Datos!C13) | E13: =UPPER(B13) | F13: =LOWER(B13) | G13: =PROPER(B13) | H13: =LEFT(B13,3) | I13: =RIGHT(B13,4) | J13: =MID(B13,2,5) | K13: =LEN(B13) | L13: =FIND(" ",B13) | M13: =SUBSTITUTE(B13," ","_") | N13: =TRIM(" "&B13&" ") | O13: =TEXT(Datos!I13,"yyyy-mm-dd") | P13: =DATE(YEAR(Datos!I13),MONTH(Datos!I13),DAY(Datos!I13)) | Q13: =YEAR(Datos!I13) | R13: =MONTH(Datos!I13) | S13: =DAY(Datos!I13) | T13: =WEEKDAY(Datos!I13,2) | U13: =EDATE(Datos!I13,2) | V13: =EOMONTH(Datos!I13,0) | W13: =TODAY()-Datos!I13 | X13: =NETWORKDAYS(Datos!I13,Datos!I13+10)
... A51: =Datos!A51 | B51: =Datos!B51&" "&Datos!C51 | C51: =CONCAT(Datos!B51," ",Datos!C51) | D51: =CONCATENATE(Datos!B51,"-",Datos!C51) | E51: =UPPER(B51) | F51: =LOWER(B51) | G51: =PROPER(B51) | H51: =LEFT(B51,3) | I51: =RIGHT(B51,4) | J51: =MID(B51,2,5) | K51: =LEN(B51) | L51: =FIND(" ",B51) | M51: =SUBSTITUTE(B51," ","_") | N51: =TRIM(" "&B51&" ") | O51: =TEXT(Datos!I51,"yyyy-mm-dd") | P51: =DATE(YEAR(Datos!I51),MONTH(Datos!I51),DAY(Datos!I51)) | Q51: =YEAR(Datos!I51) | R51: =MONTH(Datos!I51) | S51: =DAY(Datos!I51) | T51: =WEEKDAY(Datos!I51,2) | U51: =EDATE(Datos!I51,2) | V51: =EOMONTH(Datos!I51,0) | W51: =TODAY()-Datos!I51 | X51: =NETWORKDAYS(Datos!I51,Datos!I51+10)

Sheet Busquedas
A1: ID buscado | B1: VLOOKUP nombre | C1: HLOOKUP ejemplo | D1: INDEX | E1: MATCH | F1: INDEX+MATCH apellido | G1: CHOOSE | H1: LOOKUP aprox | I1: IFNA | J1: COUNTIFS | K1: SUMIFS | L1: AVERAGEIFS | N1: Codigo | O1: A | P1: B | Q1: C
N2: Nivel | O2: Bronce | P2: Plata | Q2: Oro
A3: =Datos!A2 | B3: =VLOOKUP(A3,Datos!$A$2:$K$51,2,FALSE) | C3: =HLOOKUP(CHOOSE(MOD(ROW()-3,3)+1,"A","B","C"),$O$1:$Q$2,2,FALSE) | D3: =INDEX(Datos!$B$2:$B$51,MATCH(A3,Datos!$A$2:$A$51,0)) | E3: =MATCH(A3,Datos!$A$2:$A$51,0) | F3: =INDEX(Datos!$C$2:$C$51,MATCH(A3,Datos!$A$2:$A$51,0)) | G3: =CHOOSE(MOD(ROW(),3)+1,"Rojo","Verde","Azul") | H3: =LOOKUP(Datos!F2,{1,8,15},{"Bajo","Medio","Alto"}) | I3: =IFNA(VLOOKUP(-1,Datos!$A$2:$B$51,2,FALSE),"No encontrado") | J3: =COUNTIFS(Datos!D$2:D$51,Datos!D2,Datos!J$2:J$51,Datos!J2) | K3: =SUMIFS(Calculos!C$2:C$51,Datos!D$2:D$51,Datos!D2,Datos!J$2:J$51,Datos!J2) | L3: =AVERAGEIFS(Calculos!E$2:E$51,Datos!D$2:D$51,Datos!D2,Datos!J$2:J$51,Datos!J2)
A4: =Datos!A3 | B4: =VLOOKUP(A4,Datos!$A$2:$K$51,2,FALSE) | C4: =HLOOKUP(CHOOSE(MOD(ROW()-3,3)+1,"A","B","C"),$O$1:$Q$2,2,FALSE) | D4: =INDEX(Datos!$B$2:$B$51,MATCH(A4,Datos!$A$2:$A$51,0)) | E4: =MATCH(A4,Datos!$A$2:$A$51,0) | F4: =INDEX(Datos!$C$2:$C$51,MATCH(A4,Datos!$A$2:$A$51,0)) | G4: =CHOOSE(MOD(ROW(),3)+1,"Rojo","Verde","Azul") | H4: =LOOKUP(Datos!F3,{1,8,15},{"Bajo","Medio","Alto"}) | I4: =IFNA(VLOOKUP(-1,Datos!$A$2:$B$51,2,FALSE),"No encontrado") | J4: =COUNTIFS(Datos!D$2:D$51,Datos!D3,Datos!J$2:J$51,Datos!J3) | K4: =SUMIFS(Calculos!C$2:C$51,Datos!D$2:D$51,Datos!D3,Datos!J$2:J$51,Datos!J3) | L4: =AVERAGEIFS(Calculos!E$2:E$51,Datos!D$2:D$51,Datos!D3,Datos!J$2:J$51,Datos!J3)
A5: =Datos!A4 | B5: =VLOOKUP(A5,Datos!$A$2:$K$51,2,FALSE) | C5: =HLOOKUP(CHOOSE(MOD(ROW()-3,3)+1,"A","B","C"),$O$1:$Q$2,2,FALSE) | D5: =INDEX(Datos!$B$2:$B$51,MATCH(A5,Datos!$A$2:$A$51,0)) | E5: =MATCH(A5,Datos!$A$2:$A$51,0) | F5: =INDEX(Datos!$C$2:$C$51,MATCH(A5,Datos!$A$2:$A$51,0)) | G5: =CHOOSE(MOD(ROW(),3)+1,"Rojo","Verde","Azul") | H5: =LOOKUP(Datos!F4,{1,8,15},{"Bajo","Medio","Alto"}) | I5: =IFNA(VLOOKUP(-1,Datos!$A$2:$B$51,2,FALSE),"No encontrado") | J5: =COUNTIFS(Datos!D$2:D$51,Datos!D4,Datos!J$2:J$51,Datos!J4) | K5: =SUMIFS(Calculos!C$2:C$51,Datos!D$2:D$51,Datos!D4,Datos!J$2:J$51,Datos!J4) | L5: =AVERAGEIFS(Calculos!E$2:E$51,Datos!D$2:D$51,Datos!D4,Datos!J$2:J$51,Datos!J4)
A6: =Datos!A5 | B6: =VLOOKUP(A6,Datos!$A$2:$K$51,2,FALSE) | C6: =HLOOKUP(CHOOSE(MOD(ROW()-3,3)+1,"A","B","C"),$O$1:$Q$2,2,FALSE) | D6: =INDEX(Datos!$B$2:$B$51,MATCH(A6,Datos!$A$2:$A$51,0)) | E6: =MATCH(A6,Datos!$A$2:$A$51,0) | F6: =INDEX(Datos!$C$2:$C$51,MATCH(A6,Datos!$A$2:$A$51,0)) | G6: =CHOOSE(MOD(ROW(),3)+1,"Rojo","Verde","Azul") | H6: =LOOKUP(Datos!F5,{1,8,15},{"Bajo","Medio","Alto"}) | I6: =IFNA(VLOOKUP(-1,Datos!$A$2:$B$51,2,FALSE),"No encontrado") | J6: =COUNTIFS(Datos!D$2:D$51,Datos!D5,Datos!J$2:J$51,Datos!J5) | K6: =SUMIFS(Calculos!C$2:C$51,Datos!D$2:D$51,Datos!D5,Datos!J$2:J$51,Datos!J5) | L6: =AVERAGEIFS(Calculos!E$2:E$51,Datos!D$2:D$51,Datos!D5,Datos!J$2:J$51,Datos!J5)
A7: =Datos!A6 | B7: =VLOOKUP(A7,Datos!$A$2:$K$51,2,FALSE) | C7: =HLOOKUP(CHOOSE(MOD(ROW()-3,3)+1,"A","B","C"),$O$1:$Q$2,2,FALSE) | D7: =INDEX(Datos!$B$2:$B$51,MATCH(A7,Datos!$A$2:$A$51,0)) | E7: =MATCH(A7,Datos!$A$2:$A$51,0) | F7: =INDEX(Datos!$C$2:$C$51,MATCH(A7,Datos!$A$2:$A$51,0)) | G7: =CHOOSE(MOD(ROW(),3)+1,"Rojo","Verde","Azul") | H7: =LOOKUP(Datos!F6,{1,8,15},{"Bajo","Medio","Alto"}) | I7: =IFNA(VLOOKUP(-1,Datos!$A$2:$B$51,2,FALSE),"No encontrado") | J7: =COUNTIFS(Datos!D$2:D$51,Datos!D6,Datos!J$2:J$51,Datos!J6) | K7: =SUMIFS(Calculos!C$2:C$51,Datos!D$2:D$51,Datos!D6,Datos!J$2:J$51,Datos!J6) | L7: =AVERAGEIFS(Calculos!E$2:E$51,Datos!D$2:D$51,Datos!D6,Datos!J$2:J$51,Datos!J6)
A8: =Datos!A7 | B8: =VLOOKUP(A8,Datos!$A$2:$K$51,2,FALSE) | C8: =HLOOKUP(CHOOSE(MOD(ROW()-3,3)+1,"A","B","C"),$O$1:$Q$2,2,FALSE) | D8: =INDEX(Datos!$B$2:$B$51,MATCH(A8,Datos!$A$2:$A$51,0)) | E8: =MATCH(A8,Datos!$A$2:$A$51,0) | F8: =INDEX(Datos!$C$2:$C$51,MATCH(A8,Datos!$A$2:$A$51,0)) | G8: =CHOOSE(MOD(ROW(),3)+1,"Rojo","Verde","Azul") | H8: =LOOKUP(Datos!F7,{1,8,15},{"Bajo","Medio","Alto"}) | I8: =IFNA(VLOOKUP(-1,Datos!$A$2:$B$51,2,FALSE),"No encontrado") | J8: =COUNTIFS(Datos!D$2:D$51,Datos!D7,Datos!J$2:J$51,Datos!J7) | K8: =SUMIFS(Calculos!C$2:C$51,Datos!D$2:D$51,Datos!D7,Datos!J$2:J$51,Datos!J7) | L8: =AVERAGEIFS(Calculos!E$2:E$51,Datos!D$2:D$51,Datos!D7,Datos!J$2:J$51,Datos!J7)
A9: =Datos!A8 | B9: =VLOOKUP(A9,Datos!$A$2:$K$51,2,FALSE) | C9: =HLOOKUP(CHOOSE(MOD(ROW()-3,3)+1,"A","B","C"),$O$1:$Q$2,2,FALSE) | D9: =INDEX(Datos!$B$2:$B$51,MATCH(A9,Datos!$A$2:$A$51,0)) | E9: =MATCH(A9,Datos!$A$2:$A$51,0) | F9: =INDEX(Datos!$C$2:$C$51,MATCH(A9,Datos!$A$2:$A$51,0)) | G9: =CHOOSE(MOD(ROW(),3)+1,"Rojo","Verde","Azul") | H9: =LOOKUP(Datos!F8,{1,8,15},{"Bajo","Medio","Alto"}) | I9: =IFNA(VLOOKUP(-1,Datos!$A$2:$B$51,2,FALSE),"No encontrado") | J9: =COUNTIFS(Datos!D$2:D$51,Datos!D8,Datos!J$2:J$51,Datos!J8) | K9: =SUMIFS(Calculos!C$2:C$51,Datos!D$2:D$51,Datos!D8,Datos!J$2:J$51,Datos!J8) | L9: =AVERAGEIFS(Calculos!E$2:E$51,Datos!D$2:D$51,Datos!D8,Datos!J$2:J$51,Datos!J8)
A10: =Datos!A9 | B10: =VLOOKUP(A10,Datos!$A$2:$K$51,2,FALSE) | C10: =HLOOKUP(CHOOSE(MOD(ROW()-3,3)+1,"A","B","C"),$O$1:$Q$2,2,FALSE) | D10: =INDEX(Datos!$B$2:$B$51,MATCH(A10,Datos!$A$2:$A$51,0)) | E10: =MATCH(A10,Datos!$A$2:$A$51,0) | F10: =INDEX(Datos!$C$2:$C$51,MATCH(A10,Datos!$A$2:$A$51,0)) | G10: =CHOOSE(MOD(ROW(),3)+1,"Rojo","Verde","Azul") | H10: =LOOKUP(Datos!F9,{1,8,15},{"Bajo","Medio","Alto"}) | I10: =IFNA(VLOOKUP(-1,Datos!$A$2:$B$51,2,FALSE),"No encontrado") | J10: =COUNTIFS(Datos!D$2:D$51,Datos!D9,Datos!J$2:J$51,Datos!J9) | K10: =SUMIFS(Calculos!C$2:C$51,Datos!D$2:D$51,Datos!D9,Datos!J$2:J$51,Datos!J9) | L10: =AVERAGEIFS(Calculos!E$2:E$51,Datos!D$2:D$51,Datos!D9,Datos!J$2:J$51,Datos!J9)
A11: =Datos!A10 | B11: =VLOOKUP(A11,Datos!$A$2:$K$51,2,FALSE) | C11: =HLOOKUP(CHOOSE(MOD(ROW()-3,3)+1,"A","B","C"),$O$1:$Q$2,2,FALSE) | D11: =INDEX(Datos!$B$2:$B$51,MATCH(A11,Datos!$A$2:$A$51,0)) | E11: =MATCH(A11,Datos!$A$2:$A$51,0) | F11: =INDEX(Datos!$C$2:$C$51,MATCH(A11,Datos!$A$2:$A$51,0)) | G11: =CHOOSE(MOD(ROW(),3)+1,"Rojo","Verde","Azul") | H11: =LOOKUP(Datos!F10,{1,8,15},{"Bajo","Medio","Alto"}) | I11: =IFNA(VLOOKUP(-1,Datos!$A$2:$B$51,2,FALSE),"No encontrado") | J11: =COUNTIFS(Datos!D$2:D$51,Datos!D10,Datos!J$2:J$51,Datos!J10) | K11: =SUMIFS(Calculos!C$2:C$51,Datos!D$2:D$51,Datos!D10,Datos!J$2:J$51,Datos!J10) | L11: =AVERAGEIFS(Calculos!E$2:E$51,Datos!D$2:D$51,Datos!D10,Datos!J$2:J$51,Datos!J10)
A12: =Datos!A11 | B12: =VLOOKUP(A12,Datos!$A$2:$K$51,2,FALSE) | C12: =HLOOKUP(CHOOSE(MOD(ROW()-3,3)+1,"A","B","C"),$O$1:$Q$2,2,FALSE) | D12: =INDEX(Datos!$B$2:$B$51,MATCH(A12,Datos!$A$2:$A$51,0)) | E12: =MATCH(A12,Datos!$A$2:$A$51,0) | F12: =INDEX(Datos!$C$2:$C$51,MATCH(A12,Datos!$A$2:$A$51,0)) | G12: =CHOOSE(MOD(ROW(),3)+1,"Rojo","Verde","Azul") | H12: =LOOKUP(Datos!F11,{1,8,15},{"Bajo","Medio","Alto"}) | I12: =IFNA(VLOOKUP(-1,Datos!$A$2:$B$51,2,FALSE),"No encontrado") | J12: =COUNTIFS(Datos!D$2:D$51,Datos!D11,Datos!J$2:J$51,Datos!J11) | K12: =SUMIFS(Calculos!C$2:C$51,Datos!D$2:D$51,Datos!D11,Datos!J$2:J$51,Datos!J11) | L12: =AVERAGEIFS(Calculos!E$2:E$51,Datos!D$2:D$51,Datos!D11,Datos!J$2:J$51,Datos!J11)
A13: =Datos!A12 | B13: =VLOOKUP(A13,Datos!$A$2:$K$51,2,FALSE) | C13: =HLOOKUP(CHOOSE(MOD(ROW()-3,3)+1,"A","B","C"),$O$1:$Q$2,2,FALSE) | D13: =INDEX(Datos!$B$2:$B$51,MATCH(A13,Datos!$A$2:$A$51,0)) | E13: =MATCH(A13,Datos!$A$2:$A$51,0) | F13: =INDEX(Datos!$C$2:$C$51,MATCH(A13,Datos!$A$2:$A$51,0)) | G13: =CHOOSE(MOD(ROW(),3)+1,"Rojo","Verde","Azul") | H13: =LOOKUP(Datos!F12,{1,8,15},{"Bajo","Medio","Alto"}) | I13: =IFNA(VLOOKUP(-1,Datos!$A$2:$B$51,2,FALSE),"No encontrado") | J13: =COUNTIFS(Datos!D$2:D$51,Datos!D12,Datos!J$2:J$51,Datos!J12) | K13: =SUMIFS(Calculos!C$2:C$51,Datos!D$2:D$51,Datos!D12,Datos!J$2:J$51,Datos!J12) | L13: =AVERAGEIFS(Calculos!E$2:E$51,Datos!D$2:D$51,Datos!D12,Datos!J$2:J$51,Datos!J12)
A14: =Datos!A13 | B14: =VLOOKUP(A14,Datos!$A$2:$K$51,2,FALSE) | C14: =HLOOKUP(CHOOSE(MOD(ROW()-3,3)+1,"A","B","C"),$O$1:$Q$2,2,FALSE) | D14: =INDEX(Datos!$B$2:$B$51,MATCH(A14,Datos!$A$2:$A$51,0)) | E14: =MATCH(A14,Datos!$A$2:$A$51,0) | F14: =INDEX(Datos!$C$2:$C$51,MATCH(A14,Datos!$A$2:$A$51,0)) | G14: =CHOOSE(MOD(ROW(),3)+1,"Rojo","Verde","Azul") | H14: =LOOKUP(Datos!F13,{1,8,15},{"Bajo","Medio","Alto"}) | I14: =IFNA(VLOOKUP(-1,Datos!$A$2:$B$51,2,FALSE),"No encontrado") | J14: =COUNTIFS(Datos!D$2:D$51,Datos!D13,Datos!J$2:J$51,Datos!J13) | K14: =SUMIFS(Calculos!C$2:C$51,Datos!D$2:D$51,Datos!D13,Datos!J$2:J$51,Datos!J13) | L14: =AVERAGEIFS(Calculos!E$2:E$51,Datos!D$2:D$51,Datos!D13,Datos!J$2:J$51,Datos!J13)
... A52: =Datos!A51 | B52: =VLOOKUP(A52,Datos!$A$2:$K$51,2,FALSE) | C52: =HLOOKUP(CHOOSE(MOD(ROW()-3,3)+1,"A","B","C"),$O$1:$Q$2,2,FALSE) | D52: =INDEX(Datos!$B$2:$B$51,MATCH(A52,Datos!$A$2:$A$51,0)) | E52: =MATCH(A52,Datos!$A$2:$A$51,0) | F52: =INDEX(Datos!$C$2:$C$51,MATCH(A52,Datos!$A$2:$A$51,0)) | G52: =CHOOSE(MOD(ROW(),3)+1,"Rojo","Verde","Azul") | H52: =LOOKUP(Datos!F51,{1,8,15},{"Bajo","Medio","Alto"}) | I52: =IFNA(VLOOKUP(-1,Datos!$A$2:$B$51,2,FALSE),"No encontrado") | J52: =COUNTIFS(Datos!D$2:D$51,Datos!D51,Datos!J$2:J$51,Datos!J51) | K52: =SUMIFS(Calculos!C$2:C$51,Datos!D$2:D$51,Datos!D51,Datos!J$2:J$51,Datos!J51) | L52: =AVERAGEIFS(Calculos!E$2:E$51,Datos!D$2:D$51,Datos!D51,Datos!J$2:J$51,Datos!J51)

Sheet Validaciones
A1: Entrada número (1-100) | B1: Lista departamento | C1: Fecha permitida | D1: Texto (máx 30) | E1: Resultado validación | F1: Clave compuesta
A2: 2 | B2: Ventas | C2: 46023 | D2: Prueba 2 | E2: =IF(AND(A2>=1,A2<=100),"Número OK","Número fuera") | F2: =B2&"-"&TEXT(C2,"yyyymmdd")
A3: 3 | B3: Soporte | C3: 46024 | D3: Prueba 3 | E3: =IF(AND(A3>=1,A3<=100),"Número OK","Número fuera") | F3: =B3&"-"&TEXT(C3,"yyyymmdd")
A4: 4 | B4: Finanzas | C4: 46025 | D4: Prueba 4 | E4: =IF(AND(A4>=1,A4<=100),"Número OK","Número fuera") | F4: =B4&"-"&TEXT(C4,"yyyymmdd")
A5: 5 | B5: Operaciones | C5: 46026 | D5: Prueba 5 | E5: =IF(AND(A5>=1,A5<=100),"Número OK","Número fuera") | F5: =B5&"-"&TEXT(C5,"yyyymmdd")
A6: 6 | B6: Ventas | C6: 46027 | D6: Prueba 6 | E6: =IF(AND(A6>=1,A6<=100),"Número OK","Número fuera") | F6: =B6&"-"&TEXT(C6,"yyyymmdd")
A7: 7 | B7: Soporte | C7: 46028 | D7: Prueba 7 | E7: =IF(AND(A7>=1,A7<=100),"Número OK","Número fuera") | F7: =B7&"-"&TEXT(C7,"yyyymmdd")
A8: 8 | B8: Finanzas | C8: 46029 | D8: Prueba 8 | E8: =IF(AND(A8>=1,A8<=100),"Número OK","Número fuera") | F8: =B8&"-"&TEXT(C8,"yyyymmdd")
A9: 9 | B9: Operaciones | C9: 46030 | D9: Prueba 9 | E9: =IF(AND(A9>=1,A9<=100),"Número OK","Número fuera") | F9: =B9&"-"&TEXT(C9,"yyyymmdd")
A10: 10 | B10: Ventas | C10: 46031 | D10: Prueba 10 | E10: =IF(AND(A10>=1,A10<=100),"Número OK","Número fuera") | F10: =B10&"-"&TEXT(C10,"yyyymmdd")
A11: 11 | B11: Soporte | C11: 46032 | D11: Prueba 11 | E11: =IF(AND(A11>=1,A11<=100),"Número OK","Número fuera") | F11: =B11&"-"&TEXT(C11,"yyyymmdd")
A12: 12 | B12: Finanzas | C12: 46033 | D12: Prueba 12 | E12: =IF(AND(A12>=1,A12<=100),"Número OK","Número fuera") | F12: =B12&"-"&TEXT(C12,"yyyymmdd")
A13: 13 | B13: Operaciones | C13: 46034 | D13: Prueba 13 | E13: =IF(AND(A13>=1,A13<=100),"Número OK","Número fuera") | F13: =B13&"-"&TEXT(C13,"yyyymmdd")
... A51: 51 | B51: Soporte | C51: 46072 | D51: Prueba 51 | E51: =IF(AND(A51>=1,A51<=100),"Número OK","Número fuera") | F51: =B51&"-"&TEXT(C51,"yyyymmdd")

Sheet Matrices
A1: Métrica | B1: Fórmula | C1: Nota
A2: UNIQUE | B2: =UNIQUE(Datos!D2:D51) | C2: Matriz dinámica: valores únicos
A3: SORT | B3: =SORT(Datos!B2:B51) | C3: Matriz dinámica: ordenación
A4: FILTER | B4: =FILTER(Datos!A2:K51,Datos!D2:D51="Ventas") | C4: Matriz dinámica: filas filtradas
A5: SEQUENCE | B5: =SEQUENCE(10,3,1,1) | C5: Matriz dinámica: secuencia
A6: TRANSPOSE | B6: =TRANSPOSE(Datos!B2:E6) | C6: Matriz dinámica: transposición
A7: SUMPRODUCT | B7: =SUMPRODUCT(Datos!F2:F51,Datos!G2:G51) | C7: Agregación matricial
A8: SUBTOTAL | B8: =SUBTOTAL(9,Calculos!C2:C51) | C8: Subtotal
A9: AGGREGATE | B9: =AGGREGATE(9,6,Calculos!C2:C51) | C9: Agregado con opciones
A10: LET | B10: =LET(x,Datos!F2:F51,y,Datos!G2:G51,SUMPRODUCT(x,y)) | C10: Variables locales
A11: LAMBDA | B11: =LAMBDA(x,x*2)(5) | C11: LAMBDA simple
A12: XMATCH | B12: =XMATCH(Datos!A2,Datos!A2:A51,0) | C12: Búsqueda moderna
A13: XLOOKUP | B13: =XLOOKUP(Datos!A2,Datos!A2:A51,Datos!B2:B51,"No existe") | C13: Búsqueda moderna
A14: TEXTJOIN | B14: =TEXTJOIN(", ",TRUE,Datos!B2:B6) | C14: Unión con delimitador
A15: CONCAT rango | B15: =CONCAT(Datos!B2:B4) | C15: Concatenación de rango
A16: COUNTBLANK | B16: =COUNTBLANK(Datos!A2:A51) | C16: Conteo de vacías
A17: ISNUMBER | B17: =ISNUMBER(Datos!F2) | C17: Función de información
A18: ISBLANK | B18: =ISBLANK(Datos!L2) | C18: Función de información
A19: NA | B19: =IFERROR(1/0,NA()) | C19: Error controlado
